README.txt
setup.py
rfc5424syslog/__init__.py
rfc5424syslog.egg-info/PKG-INFO
rfc5424syslog.egg-info/SOURCES.txt
rfc5424syslog.egg-info/dependency_links.txt
rfc5424syslog.egg-info/not-zip-safe
rfc5424syslog.egg-info/requires.txt
rfc5424syslog.egg-info/top_level.txt