Metadata-Version: 1.0
Name: rfc5424syslog
Version: 0.0.1
Summary: A Logging Formatter for Python's logging module to properly handle Syslog RFC5424 messages
Home-page: https://github.com/morganfainberg/python-rfc5424-logging-formatter
Author: Morgan Fainberg
Author-email: UNKNOWN
License: GPLv2
Platform: UNKNOWN
